README.md
setup.cfg
setup.py
serenytics/__init__.py
serenytics/client.py
serenytics/helpers.py
serenytics/io_tools.py
serenytics/script.py
serenytics/settings.py
serenytics/source.py
serenytics/task.py
serenytics/version.py
serenytics/webapp.py
serenytics.egg-info/PKG-INFO
serenytics.egg-info/SOURCES.txt
serenytics.egg-info/dependency_links.txt
serenytics.egg-info/requires.txt
serenytics.egg-info/top_level.txt
tests/__init__.py
tests/common.py
tests/conftest.py
tests/load_env.py
tests/test_client.py
tests/test_script.py
tests/test_source.py
tests/test_template_script_refresh_dashboard_cache.py