Metadata-Version: 1.1
Name: serenytics
Version: 2.0.1
Summary: Serenytics API client for python
Home-page: https://www.serenytics.com
Author: Serenytics Team
Author-email: support@serenytics.com
License: UNKNOWN
Keywords: serenytics,backend,hosted,cloud,bi,dashboard,scripts,etl
Platform: UNKNOWN
Classifier: License :: Other/Proprietary License
Classifier: Operating System :: OS Independent
Classifier: Development Status :: 5 - Production/Stable
Classifier: Intended Audience :: Developers
Classifier: Programming Language :: Python :: 3
Classifier: Programming Language :: Python :: 3.5
Classifier: Programming Language :: Python :: 3.6
Classifier: Programming Language :: Python :: 3.7
Classifier: Topic :: Internet
Classifier: Topic :: Internet :: WWW/HTTP
